<?xml version="1.0" encoding="UTF-8" standalone="yes"?><node artifactManager="be.nabu.eai.module.web.component.WebComponentManager" created="2018-07-05T10:05:26.344+02:00" lastModified="2019-05-26T14:43:12.339+02:00" leaf="true" version="11"><environmentId>helios</environmentId><hidden>false</hidden><properties/><references>nabu.frameworks.tasks.manage.rest.schedule.property.create</references><references>nabu.frameworks.tasks.manage.rest.schedule.property.delete</references><references>nabu.frameworks.tasks.manage.rest.schedule.property.get</references><references>nabu.frameworks.tasks.manage.rest.schedule.property.update</references><references>nabu.frameworks.tasks.manage.rest.schedule.create</references><references>nabu.frameworks.tasks.manage.rest.schedule.delete</references><references>nabu.frameworks.tasks.manage.rest.schedule.get</references><references>nabu.frameworks.tasks.manage.rest.schedule.update</references><references>nabu.frameworks.tasks.manage.rest.task.log.create</references><references>nabu.frameworks.tasks.manage.rest.task.log.delete</references><references>nabu.frameworks.tasks.manage.rest.task.log.get</references><references>nabu.frameworks.tasks.manage.rest.task.log.list</references><references>nabu.frameworks.tasks.manage.rest.task.log.update</references><references>nabu.frameworks.tasks.manage.rest.task.property.create</references><references>nabu.frameworks.tasks.manage.rest.task.property.delete</references><references>nabu.frameworks.tasks.manage.rest.task.property.get</references><references>nabu.frameworks.tasks.manage.rest.task.property.list</references><references>nabu.frameworks.tasks.manage.rest.task.property.update</references><references>nabu.frameworks.tasks.manage.rest.task.create</references><references>nabu.frameworks.tasks.manage.rest.task.delete</references><references>nabu.frameworks.tasks.manage.rest.task.get</references><references>nabu.frameworks.tasks.manage.rest.task.list</references><references>nabu.frameworks.tasks.manage.rest.task.update</references><references>nabu.frameworks.tasks.manage.rest.taskQueue.schedule.create</references><references>nabu.frameworks.tasks.manage.rest.taskQueue.schedule.delete</references><references>nabu.frameworks.tasks.manage.rest.taskQueue.schedule.get</references><references>nabu.frameworks.tasks.manage.rest.taskQueue.schedule.list</references><references>nabu.frameworks.tasks.manage.rest.taskQueue.schedule.update</references><references>nabu.frameworks.tasks.manage.rest.taskQueue.create</references><references>nabu.frameworks.tasks.manage.rest.taskQueue.delete</references><references>nabu.frameworks.tasks.manage.rest.taskQueue.get</references><references>nabu.frameworks.tasks.manage.rest.taskQueue.list</references><references>nabu.frameworks.tasks.manage.rest.taskQueue.update</references><references>nabu.frameworks.tasks.manage.rest.task.retry</references><references>nabu.frameworks.tasks.manage.rest.task.wakeup</references><references>nabu.frameworks.tasks.manage.rest.schedule.input.list</references><references>nabu.frameworks.tasks.manage.rest.schedule.input.merge</references><references>nabu.frameworks.tasks.manage.rest.schedule.list</references><references>nabu.frameworks.tasks.manage.rest.schedule.property.list</references></node>