<?xml version="1.0" encoding="UTF-8" standalone="yes"?><node artifactManager="be.nabu.eai.module.services.jdbc.JDBCServiceManager" created="2018-10-26T09:34:49.658+02:00" lastModified="2018-10-26T09:35:47.437+02:00" leaf="false" version="4"><environmentId>hyperion</environmentId><hidden>false</hidden><properties/><references>java.lang.String</references><references>java.lang.Long</references><references>java.lang.Integer</references><references>java.lang.Boolean</references><references>nabu.frameworks.tasks.database.task.cancelStaged.parameters</references><references>be.nabu.libs.types.api.KeyValuePair</references><references>java.lang.Long</references><references>java.lang.Boolean</references></node>