<?xml version="1.0" encoding="UTF-8" standalone="yes"?>
<node artifactManager="be.nabu.eai.module.types.structure.StructureManager" created="2022-11-03T13:02:07.053+01:00" lastModified="2025-02-10T13:41:02.673+01:00" leaf="true" version="26">
    <environmentId>ares</environmentId>
    <hidden>false</hidden>
    <locked>false</locked>
    <properties/>
    <references>java.util.UUID</references>
    <references>java.util.Date</references>
    <references>java.lang.String</references>
    <references>nabu.frameworks.tasks.types.model.tasks.Task</references>
    <references>java.lang.Long</references>
    <references>nabu.frameworks.tasks.types.model.tasks.TaskQueue</references>
    <references>nabu.frameworks.tasks.types.model.tasks.TaskSchedule</references>
    <references>java.lang.Boolean</references>
</node>
